pydigital/__init__.py
pydigital/linecoding.py
pydigital/parity_generation.py
pydigital/utils.py
PyDigital-1.1.1.dist-info/LICENSE
PyDigital-1.1.1.dist-info/METADATA
PyDigital-1.1.1.dist-info/WHEEL
PyDigital-1.1.1.dist-info/top_level.txt
PyDigital-1.1.1.dist-info/RECORD
