Metadata-Version: 2.1
Name: PyDigital
Version: 1.1.1
Summary: A python package intended for visualizing digital data line coding, generating parity bits and detecting errors in parity encoded binary data
Author-email: Sanjay S <sanjusuresh2001@gmail.com>, Prathish K V <prathishvijayakumar@gmail.com>
Project-URL: Repository, https://github.com/RapidCompiler/pydigital
Project-URL: Bug Tracker, https://github.com/RapidCompiler/pydigital/issues
Project-URL: Documentation, http://pydigital-docs.readthedocs.io/
Classifier: Programming Language :: Python :: 3
Classifier: License :: OSI Approved :: MIT License
Classifier: Operating System :: OS Independent
Requires-Python: >=3.7
License-File: LICENSE
Requires-Dist: matplotlib (>=3.6.0)
Requires-Dist: numpy (>=1.23.3)
